python_dataporten_auth-2.0.0.dist-info/RECORD
python_dataporten_auth-2.0.0.dist-info/top_level.txt
python_dataporten_auth-2.0.0.dist-info/DESCRIPTION.rst
python_dataporten_auth-2.0.0.dist-info/WHEEL
python_dataporten_auth-2.0.0.dist-info/metadata.json
python_dataporten_auth-2.0.0.dist-info/METADATA
dataporten/social.py
dataporten/__init__.py
