Metadata-Version: 2.0
Name: python-dataporten-auth
Version: 2.0.0
Summary: A plugin for python-social-auth to authenticate with dataporten
Home-page: https://github.com/UNINETT/python-dataporten-auth
Author: Hanne Moa
Author-email: hanne.moa@uninett.no
License: MIT
Keywords: django,oauth2
Platform: any
Classifier: Environment :: Web Environment
Classifier: Intended Audience :: Developers
Classifier: License :: OSI Approved :: MIT License
Classifier: Operating System :: OS Independent
Classifier: Programming Language :: Python
Classifier: Programming Language :: Python :: 3.4
Classifier: Programming Language :: Python :: 3.5
Classifier: Programming Language :: Python :: 3.6
Classifier: Framework :: Django
Classifier: Framework :: Flask
Classifier: Framework :: Pyramid
Classifier: Topic :: Internet :: WWW/HTTP
Classifier: Topic :: Software Development :: Libraries :: Python Modules
Classifier: Topic :: Utilities
Requires-Dist: social-auth-core
